postgres_dynamic/__init__.py
postgres_dynamic/pgd_get.py
postgres_dynamic/pgd_transaction.py
postgres_dynamic-0.0.11.dist-info/LICENSE
postgres_dynamic-0.0.11.dist-info/METADATA
postgres_dynamic-0.0.11.dist-info/WHEEL
postgres_dynamic-0.0.11.dist-info/top_level.txt
postgres_dynamic-0.0.11.dist-info/RECORD
