Metadata-Version: 2.1
Name: postgres-dynamic
Version: 0.0.11
Summary: Postgres Dynamic Query
Author-email: Bayu Satria Gemilang <bayu.code.lab@gmail.com>
Project-URL: Homepage, https://github.com/bayu-code-lab/postgres-dynamic
Project-URL: Bug Tracker, https://github.com/bayu-code-lab/postgres-dynamic/issues
Classifier: Programming Language :: Python :: 3
Classifier: License :: OSI Approved :: MIT License
Classifier: Operating System :: OS Independent
Requires-Python: >=3.7
License-File: LICENSE
